cusfpredict/__init__.py
cusfpredict/gfs.py
cusfpredict/predict.py
cusfpredict/reader.py
cusfpredict/utils.py
cusfpredict-0.2.1.dist-info/LICENSE
cusfpredict-0.2.1.dist-info/WHEEL
cusfpredict-0.2.1.dist-info/METADATA
cusfpredict-0.2.1.dist-info/RECORD
