Metadata-Version: 2.1
Name: cusfpredict
Version: 0.2.1
Summary: CUSF Predictor Wrapper & GFS Downloader
Author: Mark Jessop
Requires-Python: >=3.6,<4.0
Classifier: Programming Language :: Python :: 3
Classifier: Programming Language :: Python :: 3.6
Classifier: Programming Language :: Python :: 3.7
Classifier: Programming Language :: Python :: 3.8
Requires-Dist: cfgrib (>=0.9.8,<0.10.0)
Requires-Dist: fastkml (>=0.11,<0.12)
Requires-Dist: numpy (>=1.17,<2.0)
Requires-Dist: python-dateutil (>=2.8.1,<3.0.0)
Requires-Dist: pytz (>=2020.5,<2021.0)
Requires-Dist: requests (>=2.25.1,<3.0.0)
Requires-Dist: shapely (>=1.7.1,<2.0.0)
Requires-Dist: xarray (>=0.16.2,<0.17.0)
